[
    {
        "selector": ".axis-domain, .axis-tick, .axis-label",
        "effects": [
            {
                "type": "fade",
                "duration": 200
            }
        ]
    },
    {
        "reference": "start after previous",
        "id": "yearAni",
        "selector": ".symbol, .text",
        "grouping": {
            "groupBy": "year",
            "reference": "start after previous"
        },
        "effects": [
            {
                "type": "fade",
                "duration": 200
            }
        ]
    },
    {
        "reference": "start after previous",
        "selector": ".link",
        "align": {
            "target": "yearAni",
            "type": "element",
            "merge": true
        },
        "effects": [
            {
                "type": "grow",
                "duration": 600
            }
        ]
    }
]